{
	"id":"",
	"in":"",
	"out":"",
	"Label":"",
	"Name":"",
	"Value":"",
	"ConnectionType":"",
	"PinType":"Blueprints__EdgePinType.json",
	"PinTypeSelected":"HistoryPin",
	"Timestamp":"",
	"UserId":"",
	"UserPid":"",
	"Presentation":{
		"InputPin":{
			"Position":["Top", "TopRight", "Right", "BottomRight", "Bottom", "BottomLeft", "Left", "TopLeft"],
			"PositionSelected": 0,
			"ColorMode":["Important", "Normal", "Danger", "Warning", "Disabled", "Died"],
			"Color":"#000000"
		},
		"OutputPin":{
			"Position":["Top", "TopRight", "Right", "BottomRight", "Bottom", "BottomLeft", "Left", "TopLeft"],
			"PositionSelected": 0,
			"ColorMode":["Important", "Normal", "Danger", "Warning", "Disabled", "Died"],
			"Color":"#000000"
		},
		"Path":{
			"PathMode":["Internal", "External"],
			"PathModeSelected": 0,
			"ColorMode":["Important", "Normal", "Danger", "Warning", "Disabled", "Died"],
			"Color":"#000000",
			"PathDecoration":["Dashed", "Normal", "Dotted", "Custom"],
			"PathDashArray":20,
			"PathThickness":["1", "2", "3", "4", "5", "6", "7", "8", "9", "10"]
		}
	}
}